{"Category": "Switch", "InstanceId": "100976", "Scale": 0.2, "Movable_link": {"link_0": {"link_id": "link_0", "link_name": "toggle_button", "joint_type": "hinge"}, "link_1": {"link_id": "link_1", "link_name": "toggle_button", "joint_type": "hinge"}}, "Orientation": [0, 0.7071068, 0, 0.7071068], "MaxBBox": [0.703183, 0.691742, 0.141919], "MinBBox": [-0.710162, -0.721603, -0.104239], "Offset_z": 0.0208478, "Direction": [[-1, 0, 1], [1, 0, -1], [-1, 0, -1], [1, 0, 1], [0, 0, 1], [0, 0, -1]], "Effect": [], "Cause": [{"JointId": 1, "IsSmallCause": 1, "IsLargeCause": 0}, {"JointId": 2, "IsSmallCause": 1, "IsLargeCause": 0}]}